README
setup.cfg
setup.py
python_targetpay.egg-info/PKG-INFO
python_targetpay.egg-info/SOURCES.txt
python_targetpay.egg-info/dependency_links.txt
python_targetpay.egg-info/requires.txt
python_targetpay.egg-info/top_level.txt
targetpay/__init__.py
targetpay/core.py
targetpay/utils.py