Metadata-Version: 1.1
Name: python-targetpay
Version: 1.0
Summary: Python payment module for targetpay.com
Home-page: https://github.com/BalkanTech/targetpay
Author: Arjan van Eersel
Author-email: arjan@balkan.tech
License: UNKNOWN
Download-URL: https://github.com/BalkanTech/targetpay/tarball/1.0
Keywords: payment,targetpay.com,ideal,mr cash,sofort
Platform: UNKNOWN
